bdist_venv2
