Metadata-Version: 1.1
Name: bdist-venv2
Version: 0.1.3
Summary: Python distutils extension to create virtualenv built distributions.
Home-page: http://github.com/bninja/bdist-venv2
Author: me
Author-email: me@aitmp.com
License: BSD
Platform: any
Classifier: Intended Audience :: Developers
Classifier: License :: OSI Approved :: BSD License
Classifier: Operating System :: OS Independent
Classifier: Programming Language :: Python
Classifier: Topic :: Software Development :: Build Tools
Classifier: Topic :: Software Development :: Libraries :: Python Modules
